{
  "objectInfo" : {
    "id" : "6VhYDmZeBu1j4SRz7dNVGq",
    "name" : "mplt_adt_src",
    "type" : "MAPPLET",
    "metadata" : {
      "modelVersion" : {
        "major" : 0,
        "minor" : 0
      },
      "repoInfo" : {
        "repoHandle" : "0100950L00000000000Y"
      },
      "contextAttributes" : [ {
        "name" : "id",
        "value" : "@1"
      } ],
      "additionalInfo" : {
        "description" : null,
        "contentType" : "JSON",
        "documentState" : "VALID"
      }
    }
  },
  "dataFileExtension" : "zip",
  "objectRefs" : [ ]
}